levels-0.0.2.dist-info/METADATA
levels-0.0.2.dist-info/WHEEL
levels-0.0.2.dist-info/entry_points.txt
levels/__init__.py
levels/__main__.py
levels/levels.py
levels-0.0.2.dist-info/RECORD
