Metadata-Version: 2.1
Name: levels
Version: 0.0.2
Summary: LEVELS [of depth] - a vertical view of nested Python datastructures and JSON.
Keywords: data,nested,view,levels
Author-Email: Emil Bisgaard Commerou <emil@commerou.dk>
License: MIT
Classifier: Development Status :: 3 - Alpha
Classifier: Intended Audience :: Developers
Classifier: License :: OSI Approved :: MIT License
Classifier: Programming Language :: Python :: 3
Classifier: Programming Language :: Python :: 3.9
Classifier: Programming Language :: Python :: 3.10
Classifier: Programming Language :: Python :: 3.11
Classifier: Programming Language :: Python :: 3.12
Classifier: Topic :: Software Development :: Libraries :: Python Modules
Requires-Python: >=3.9
